Metadata-Version: 2.1
Name: py-singleton
Version: 1.0.0
Summary: singleton pattern for python 2 and 3
Home-page: https://github.com/randydu/py-singleton.git
Author: randydu
Author-email: randydu@gmail.com
License: MIT
Download-URL: https://github.com/randydu/py-singleton/archive/v1.0.0.tar.gz
Keywords: singleton
Platform: UNKNOWN
Classifier: Development Status :: 5 - Production/Stable
Classifier: Intended Audience :: Developers
Classifier: Operating System :: OS Independent
Classifier: Topic :: Software Development :: Libraries
Classifier: Topic :: Software Development :: Libraries :: Python Modules
Classifier: License :: OSI Approved :: MIT License
Classifier: Programming Language :: Python :: 2
Classifier: Programming Language :: Python :: 3
